[
  {
    "desc": "Stream video and filter with canvas",
    "url": "demos/gum-canvas.html",
    "tags": "getUserMedia canvas",
    "support": {
      "live": "",
      "nightly": "chrome opera"
    },
    "test": "navigator.getUserMedia !== undefined"
  },
  {
    "desc": "Stream video to the browser<br><small>Also works on Opera Mobile 12</small>",
    "url": "demos/gum.html",
    "tags": "getUserMedia",
    "support": {
      "live": "",
      "nightly": "chrome opera"
    },
    "test": "navigator.getUserMedia !== undefined"
  },
  {
    "desc": "Drag and drop and XHR upload",
    "url": "demos/dnd-upload.html",
    "tags": "file dnd xhr2",
    "support": {
      "live": "chrome firefox",
      "nightly": "ie"
    },
    "test": "typeof FileReader != 'undefined' && 'draggable' in document.createElement('span') && !!window.FormData && 'upload' in new XMLHttpRequest"
  },
  {
    "desc": "Hidden property",
    "url": "demos/hidden.html",
    "tags": "hidden",
    "support": {
      "live": "chrome firefox opera safari",
      "nightly": ""
    },
    "test": "'hidden' in document.createElement('i')"
  },
  {
    "desc": "Simple class manipulation",
    "url": "demos/classlist.html",
    "tags": "classlist",
    "support": {
      "live": "chrome opera firefox safari",
      "nightly": ""
    },
    "test": "'classList' in document.createElement('i')"
  },
  {
    "desc": "Storage events",
    "url": "demos/storage-events.html",
    "tags": "storage",
    "support": {
      "live": "chrome safari opera firefox ie"
    },
    "test": "Modernizr.localstorage"
  },
  {
    "desc": "dataset (data-* attributes)",
    "url": "demos/dataset.html",
    "tags": "dataset",
    "support": {
      "live": "chrome opera safari firefox",
      "nightly": ""
    },
    "test": "'dataset' in document.createElement('i')"
  },
  {
    "desc": "History API using pushState",
    "url": "demos/history.html",
    "notes": "Uses onpopstate event",
    "tags": "history",
    "support": {
      "live": "chrome safari firefox opera"
    },
    "test": "Modernizr.history"
  },
  {
    "desc": "Browser based file reading",
    "url": "demos/file-api-simple.html",
    "note": "Not part of HTML5",
    "tags": "file-api",
    "support": {
      "live": "firefox chrome opera"
    },
    "test": "typeof FileReader != 'undefined'"
  },
  {
    "desc": "Drag files directly into your browser",
    "url": "demos/file-api.html",
    "note": "Not directly part of HTML5",
    "tags": "file-api dnd",
    "support": {
      "live": "firefox chrome"
    },
    "test": "typeof FileReader != 'undefined' && Modernizr.draganddrop"
  },
  {
    "desc": "Simple chat client",
    "url": "demos/web-socket.html",
    "tags": "websocket",
    "support": {
      "live": "safari chrome",
      "nightly": "firefox opera"
    },
    "test": "Modernizr.websockets"
  },
  {
    "desc": "Two videos playing in sync",
    "url": "demos/two-videos.html",
    "tags": "video",
    "support": {
      "live": "firefox opera safari chrome ie"
    },
    "test": "Modernizr.video"
  },
  {
    "desc": "Interactive canvas gradients",
    "url": "demos/canvas-grad.html",
    "tags": "canvas",
    "support": {
      "live": "firefox opera safari chrome ie"
    },
    "test": "Modernizr.canvas"
  },
  {
    "desc": "Canvas & Video",
    "url": "demos/video-canvas.html",
    "tags": "video canvas",
    "support": {
      "live": "firefox opera safari chrome ie"
    },
    "test": "Modernizr.video && Modernizr.canvas"
  },
  {
    "desc": "Video",
    "url": "demos/video.html",
    "tags": "video",
    "support": {
      "live": "firefox opera safari chrome ie"
    },
    "test": "Modernizr.video"
  },
  {
    "desc": "Canvas",
    "url": "demos/demos/canvas.html",
    "tags": "canvas",
    "support": {
      "live": "firefox opera safari chrome ie"
    },
    "test": "Modernizr.canvas"
  },
  {
    "desc": "Content Editable",
    "url": "demos/contenteditable.html",
    "tags": "contenteditable storage",
    "support": {
      "live": "ie firefox opera safari chrome"
    },
    "test": "'isContentEditable' in document.createElement('span');"
  },
  {
    "desc": "Geolocation",
    "url": "demos/geo.html",
    "tags": "geolocation",
    "note": "Works on Safari Mobile too",
    "support": {
      "live": "firefox chrome safari opera ie"
    },
    "test": "Modernizr.geolocation"
  },
  {
    "desc": "postMessage",
    "url": "demos/postmessage.html",
    "note": "same domain",
    "tags": "postMessage",
    "support": {
      "live": "ie firefox opera safari chrome"
    },
    "test": "Modernizr.postmessage"
  },
  {
    "desc": "postMessage",
    "url": "demos/postmessage2.html",
    "tags": "postMessage",
    "note": "cross domain",
    "support": {
      "live": "ie firefox opera safari chrome"
    },
    "test": "Modernizr.postmessage"
  },
  {
    "desc": "drag and drop",
    "url": "demos/drag.html",
    "tags": "dnd",
    "support": {
      "live": "ie firefox safari chrome"
    },
    "test": "Modernizr.draganddrop"
  },
  {
    "desc": "drag anything",
    "url": "demos/drag-anything.html",
    "tags": "dnd",
    "support": {
      "live": "ie firefox safari chrome"
    },
    "test": "Modernizr.draganddrop"
  },
  {
    "desc": "offline detection",
    "url": "demos/offline.html",
    "tags": "offline events",
    "note": "Works on Safari Mobile too",
    "support": {
      "live": "firefox opera"
    }
  },
  {
    "desc": "navigator.onLine tests",
    "url": "demos/nav-online.html",
    "tags": "offline",
    "note": "Doesn't use events, only polls",
    "support": {
      "live": "firefox opera ie"
    }
  },
  {
    "desc": "on/offline event tests",
    "url": "demos/offline-events.html",
    "notes": "Opera &amp; Firefox - requires \"Work Offline\"",
    "tags": "offline events",
    "support": {
      "live": "firefox opera"
    }
  },
  {
    "desc": "offline application using the manifest",
    "url": "demos/offlineapp.html",
    "note": "FF 3.6 is still buggy - doesn't request manifest after initial load",
    "tags": "offline manifest",
    "support": {
      "live": "firefox safari chrome opera"
    },
    "test": "Modernizr.applicationcache"
  },
  {
    "desc": "Storage",
    "url": "demos/storage.html",
    "tags": "storage",
    "support": {
      "live": "ie firefox opera safari chrome"
    },
    "test": "Modernizr.sessionstorage && Modernizr.localstorage"
  },
  {
    "desc": "Web SQL Database Storage",
    "url": "demos/database.html",
    "tags": "sql-database",
    "support": {
      "live": "safari chrome opera"
    },
    "test": "Modernizr.websqldatabase"
  },
  {
    "desc": "Web SQL Database - rollback test",
    "url": "demos/database-rollback.html",
    "tags": "sql-database",
    "support": {
      "live": "safari chrome opera"
    },
    "test": "Modernizr.websqldatabase"
  },
  {
    "desc": "Web Workers",
    "url": "demos/worker.html",
    "tags": "workers",
    "note": "watch out - uses a lot of CPU! <a href=\"non-worker\">example without - will hang your browser</a>",
    "support": {
      "live": "safari chrome firefox opera"
    },
    "test": "Modernizr.webworkers"
  }
]
